k_peg_hanoi/__init__.py
k_peg_hanoi/py.typed
k_peg_hanoi-0.2.4.dist-info/METADATA
k_peg_hanoi-0.2.4.dist-info/WHEEL
k_peg_hanoi-0.2.4.dist-info/entry_points.txt
k_peg_hanoi-0.2.4.dist-info/licenses/LICENSE
k_peg_hanoi-0.2.4.dist-info/RECORD
