Metadata-Version: 2.4
Name: k-peg-hanoi
Version: 0.2.4
Summary: Tower of Hanoi (using k peg)
Project-URL: docs, https://saitotsutomu.github.io/k-peg-hanoi/
Project-URL: homepage, https://github.com/SaitoTsutomu/k-peg-hanoi
Author-email: Saito Tsutomu <tsutomu7@hotmail.co.jp>
License: Apache-2.0
License-File: LICENSE
Classifier: Development Status :: 1 - Planning
Classifier: License :: OSI Approved :: Apache Software License
Classifier: Programming Language :: Python
Classifier: Topic :: Scientific/Engineering
Classifier: Topic :: Software Development
Requires-Python: >=3.11
Requires-Dist: fire>=0.7.0
